fluentcron/__init__.py
fluentcron/py.typed
fluentcron/schedule.py
fluentcron/shortcuts.py
fluentcron/tests.py
fluentcron/types.py
fluentcron-0.1.1.dist-info/METADATA
fluentcron-0.1.1.dist-info/WHEEL
fluentcron-0.1.1.dist-info/licenses/LICENSE
fluentcron-0.1.1.dist-info/RECORD
