Metadata-Version: 2.4
Name: fluentcron
Version: 0.1.1
Summary: A fluent interface for constructing crontab schedules
Project-URL: Homepage, https://gitlab.com/thelabnyc/fluentcron
Project-URL: Documentation, https://gitlab.com/thelabnyc/fluentcron
Project-URL: Repository, https://gitlab.com/thelabnyc/fluentcron
Author-email: thelab <thelabdev@thelab.co>
License: ISC
License-File: LICENSE
Requires-Python: >=3.13
